README.rst
setup.py
arundeckrun.egg-info/PKG-INFO
arundeckrun.egg-info/SOURCES.txt
arundeckrun.egg-info/dependency_links.txt
arundeckrun.egg-info/requires.txt
arundeckrun.egg-info/top_level.txt
integration-tests/__init__.py
integration-tests/test_api.py
integration-tests/test_client.py
integration-tests/test_connection.py
rundeck/__init__.py
rundeck/api.py
rundeck/client.py
rundeck/connection.py
rundeck/defaults.py
rundeck/rd_exceptions.py
rundeck/transforms.py
rundeck/util.py