Metadata-Version: 1.1
Name: arundeckrun
Version: 0.2.3
Summary: A Rundeck API Python client
Home-page: https://github.com/antillion/arundeckrun
Author: otupman@antillion.com
Author-email: otupman@antillion.com
License: http://creativecommons.org/licenses/by-sa/3.0/
Platform: UNKNOWN
Classifier: Development Status :: 4 - Beta
Classifier: Intended Audience :: Developers
Classifier: Intended Audience :: Information Technology
Classifier: Intended Audience :: System Administrators
Classifier: Operating System :: OS Independent
Classifier: Programming Language :: Python :: 2.7
Classifier: Topic :: System :: Software Distribution
Classifier: Topic :: System :: Systems Administration
Classifier: Topic :: Utilities
